pyheadspace/__init__.py
pyheadspace/__main__.py
pyheadspace/auth.py
pyheadspace-3.1.5.dist-info/entry_points.txt
pyheadspace-3.1.5.dist-info/WHEEL
pyheadspace-3.1.5.dist-info/METADATA
pyheadspace-3.1.5.dist-info/RECORD
