Metadata-Version: 2.1
Name: pyheadspace
Version: 3.1.5
Summary: Command line script to download packs and singles from Headspace.
Home-page: https://github.com/yashrathi-git/pyHeadspace
Author: Yash Rathi
Author-email: yashrathicricket@gmail.com
Requires-Python: >=3.7,<4.0.0
Classifier: Programming Language :: Python :: 3
Classifier: Programming Language :: Python :: 3.10
Classifier: Programming Language :: Python :: 3.7
Classifier: Programming Language :: Python :: 3.8
Classifier: Programming Language :: Python :: 3.9
Requires-Dist: PyJWT (>=2.3.0,<3.0.0)
Requires-Dist: appdirs (>=1.4.4,<2.0.0)
Requires-Dist: click (>=8.0.3,<9.0.0)
Requires-Dist: requests (>=2.26.0,<3.0.0)
Requires-Dist: rich (>=12.2.0,<13.0.0)
Project-URL: Bug Tracker, https://github.com/yashrathi-git/pyHeadspace/issues
Project-URL: Documentation, https://github.com/yashrathi-git/pyHeadspace#pyheadspace
